DESCRIPTION.md
LICENSE
MANIFEST.in
README.md
setup.py
PySGI.egg-info/PKG-INFO
PySGI.egg-info/SOURCES.txt
PySGI.egg-info/dependency_links.txt
PySGI.egg-info/requires.txt
PySGI.egg-info/top_level.txt
pysgi/__init__.py
pysgi/_print.py
pysgi/_request.py
pysgi/_sockethandler.py
pysgi/plugins.py
pysgi/response.py
pysgi/route.py
pysgi/wsgi.py